pypicosdk/README.md
pypicosdk/__init__.py
pypicosdk/_config.py
pypicosdk/_exceptions.py
pypicosdk/base.py
pypicosdk/common.py
pypicosdk/constants.py
pypicosdk/error_list.py
pypicosdk/ps6000a.py
pypicosdk/psospa.py
pypicosdk/pypicosdk.py
pypicosdk/streaming.py
pypicosdk/version.py
pypicosdk/_classes/__init__.py
pypicosdk/_classes/_channel_class.py
pypicosdk/_classes/_general.py
pypicosdk/shared/__init__.py
pypicosdk/shared/_protocol.py
pypicosdk/shared/ps6000a_ps4000a.py
pypicosdk/shared/ps6000a_psospa.py
pypicosdk-1.6.4.dist-info/METADATA
pypicosdk-1.6.4.dist-info/WHEEL
pypicosdk-1.6.4.dist-info/licenses/LICENSE
pypicosdk-1.6.4.dist-info/RECORD
