Metadata-Version: 2.4
Name: pypicosdk
Version: 1.6.4
Summary: Modern Python wrapper for PicoSDK
Project-URL: Documentation, https://picotech.github.io/pyPicoSDK/
Project-URL: github, https://github.com/picotech/pyPicoSDK
Author-email: Pico Technology <support@picotech.com>
License: Copyright © 2025 Pico Technology Ltd.
License-File: LICENSE
Keywords: electronic,hardware,measurement,test
Classifier: Development Status :: 1 - Planning
Classifier: Operating System :: Microsoft :: Windows
Classifier: Operating System :: Microsoft :: Windows :: Windows 10
Classifier: Operating System :: Microsoft :: Windows :: Windows 11
Classifier: Programming Language :: Python :: 3
Requires-Python: >=3.10
Requires-Dist: numpy
Provides-Extra: test
Requires-Dist: pytest; extra == 'test'
